pytest_missing_modules/__init__.py
pytest_missing_modules/__version__.py
pytest_missing_modules/plugin.py
pytest_missing_modules-0.2.1.dist-info/METADATA
pytest_missing_modules-0.2.1.dist-info/WHEEL
pytest_missing_modules-0.2.1.dist-info/entry_points.txt
pytest_missing_modules-0.2.1.dist-info/licenses/LICENSE.md
pytest_missing_modules-0.2.1.dist-info/RECORD
