Metadata-Version: 2.3
Name: pytest-missing-modules
Version: 0.2.1
Summary: Pytest plugin to easily fake missing modules
Project-URL: Changelog, https://github.com/jeertmans/pytest-missing-modules/releases
Project-URL: Documentation, https://github.com/jeertmans/pytest-missing-modules
Project-URL: Founding, https://github.com/sponsors/jeertmans
Project-URL: Homepage, https://github.com/jeertmans/pytest-missing-modules
Project-URL: Repository, https://github.com/jeertmans/pytest-missing-modules
Author-email: Jérome Eertmans <jeertmans@icloud.com>
License-Expression: MIT
License-File: LICENSE.md
Keywords: missing,mocking,modules,plugin,pytest,testing
Classifier: Framework :: Pytest
Classifier: License :: OSI Approved :: MIT License
Classifier: Operating System :: OS Independent
Classifier: Programming Language :: Python :: 3
Classifier: Programming Language :: Python :: 3.8
Classifier: Programming Language :: Python :: 3.9
Classifier: Programming Language :: Python :: 3.10
Classifier: Programming Language :: Python :: 3.11
Classifier: Programming Language :: Python :: 3.12
Classifier: Topic :: Software Development :: Testing
Requires-Python: >=3.8
Requires-Dist: pytest>=8.3.2
Requires-Dist: typing-extensions>=4.12.2; python_version < '3.10'
